twelvedata/__init__.py
twelvedata/_version.py
twelvedata/client.py
twelvedata/context.py
twelvedata/endpoints.py
twelvedata/exceptions.py
twelvedata/http_client.py
twelvedata/mixins.py
twelvedata/renders.py
twelvedata/time_series.py
twelvedata/utils.py
twelvedata/websocket.py
twelvedata-1.2.28.dist-info/AUTHORS.rst
twelvedata-1.2.28.dist-info/LICENSE.txt
twelvedata-1.2.28.dist-info/METADATA
twelvedata-1.2.28.dist-info/WHEEL
twelvedata-1.2.28.dist-info/top_level.txt
twelvedata-1.2.28.dist-info/RECORD
