Metadata-Version: 2.1
Name: twelvedata
Version: 1.2.28
Summary: Python client for Twelve Data
Home-page: https://github.com/twelvedata/twelvedata-python
Author: Twelve Data
Author-email: info@twelvedata.com
License: MIT
Platform: any
Classifier: Development Status :: 4 - Beta
Classifier: Programming Language :: Python
Requires-Python: !=3.0.*,!=3.1.*,!=3.2.*,!=3.3.*,!=3.4.*,>=2.7
License-File: LICENSE.txt
License-File: AUTHORS.rst
Requires-Dist: pytimeparse<2,>=1.1
Requires-Dist: requests<3,>=2.22
Provides-Extra: matplotlib
Requires-Dist: matplotlib<3,>=2.2; python_version < "3" and extra == "matplotlib"
Requires-Dist: matplotlib>=2.2; python_version >= "3" and extra == "matplotlib"
Provides-Extra: mplfinance
Requires-Dist: mplfinance>=0.12; extra == "mplfinance"
Provides-Extra: pandas
Requires-Dist: pandas<0.25,>=0.24; python_version < "3" and extra == "pandas"
Requires-Dist: pandas>=0.24; python_version >= "3" and extra == "pandas"
Provides-Extra: plotly
Requires-Dist: plotly>=4.2.1; extra == "plotly"
Provides-Extra: testing
Requires-Dist: pytest; extra == "testing"
Requires-Dist: pytest-cov; extra == "testing"
Provides-Extra: websocket
Requires-Dist: websocket-client>=1.2.1; extra == "websocket"
